CRM_PricingTools/__init__.py
CRM_PricingTools/clean.py
CRM_PricingTools-0.0.1.dist-info/LICENSE
CRM_PricingTools-0.0.1.dist-info/METADATA
CRM_PricingTools-0.0.1.dist-info/WHEEL
CRM_PricingTools-0.0.1.dist-info/top_level.txt
CRM_PricingTools-0.0.1.dist-info/RECORD
