Metadata-Version: 2.1
Name: CRM-PricingTools
Version: 0.0.1
Summary: CRM SDK for pricing models
Home-page: UNKNOWN
Author: Antonio Moreno Martín
Author-email: ant.moreno.martin@gmail.com
License: UNKNOWN
Platform: UNKNOWN
Classifier: Programming Language :: Python :: 3
Classifier: License :: OSI Approved :: MIT License
Classifier: Operating System :: OS Independent
Requires-Python: >=3.6
